AUTHORS.rst
HISTORY.rst
LICENSE
MANIFEST.in
Makefile
README.md
setup.py
unshortenit/__init__.py
unshortenit/base.py
unshortenit.egg-info/PKG-INFO
unshortenit.egg-info/SOURCES.txt
unshortenit.egg-info/dependency_links.txt
unshortenit.egg-info/not-zip-safe
unshortenit.egg-info/requires.txt
unshortenit.egg-info/top_level.txt