Metadata-Version: 1.1
Name: unshortenit
Version: 0.2.0
Summary: Unshortens adf.ly, adfoc.us, lnx.lu, linkbucks, sh.st, and any 301 redirected shortener urls
Home-page: https://github.com/DevKeh/unshortenit
Author: Jeff Kehler
Author-email: jeffrey.kehler@gmail.com
License: MIT
Keywords: unshortener adf.ly linkbucks lnx.lu adfoc.us sh.st shortener
Platform: UNKNOWN
Classifier: Development Status :: 3 - Alpha
Classifier: Intended Audience :: Developers
Classifier: License :: OSI Approved :: MIT License
Classifier: Natural Language :: English
Classifier: Programming Language :: Python
